README.md
setup.py
base/__init__.py
coding/__init__.py
files/__init__.py
icaria.egg-info/PKG-INFO
icaria.egg-info/SOURCES.txt
icaria.egg-info/dependency_links.txt
icaria.egg-info/top_level.txt
javascript/__init__.py
multitasking/__init__.py
net/__init__.py
pretty/__init__.py
strings/__init__.py