Metadata-Version: 2.1
Name: icaria
Version: 1.0.2
Summary: Providing intelligent API suggestions as you type
Author: N0P3
Author-email: n0p3@qq.com
